{
  "bankList": {
    "success": true,
    "code": null,
    "message": "",
    "content": {
      "user": {
        "name": "홍길동",
        "age": 30
      },
      "bankList": [
        {
          "id": 1,
          "bankCode": "011",
          "bankName": "신한은행"
        },
        {
          "id": 2,
          "bankCode": "012",
          "bankName": "국민은행"
        },
        {
          "id": 3,
          "bankCode": "013",
          "bankName": "우리은행"
        },
        {
          "id": 4,
          "bankCode": "014",
          "bankName": "농협은행"
        },
        {
          "id": 5,
          "bankCode": "015",
          "bankName": "기업은행"
        }
      ]
    }
  }
}